thirukkural/__init__.py
thirukkural/kural.db
thirukkural-1.1.dist-info/LICENSE.txt
thirukkural-1.1.dist-info/METADATA
thirukkural-1.1.dist-info/WHEEL
thirukkural-1.1.dist-info/entry_points.txt
thirukkural-1.1.dist-info/top_level.txt
thirukkural-1.1.dist-info/RECORD
