Metadata-Version: 2.1
Name: thirukkural
Version: 1.1
Summary: Thirukkural for command-line and python module
Home-page: https://github.com/VaasuDevanS/thirukkural-cl
Author: Vaasudevan Srinivasan
Author-email: vaasuceg.96@gmail.com
License: LICENSE.txt
Platform: UNKNOWN
Classifier: Operating System :: OS Independent
Classifier: Programming Language :: Python :: 3
Classifier: Programming Language :: Python :: 3.3
Classifier: Programming Language :: Python :: 3.4
Classifier: Programming Language :: Python :: 3.5
Classifier: Programming Language :: Python :: 3.6
Classifier: Programming Language :: Python :: 3.7
